parcoursup_dataviz/__init__.py
parcoursup_dataviz/cli.py
parcoursup_dataviz/scraper.py
parcoursup_dataviz/table.py
parcoursup_dataviz/table_template.html
parcoursup_dataviz/visualizer.py
parcoursup_dataviz-0.2.0.dist-info/entry_points.txt
parcoursup_dataviz-0.2.0.dist-info/WHEEL
parcoursup_dataviz-0.2.0.dist-info/METADATA
parcoursup_dataviz-0.2.0.dist-info/RECORD
