Metadata-Version: 2.1
Name: parcoursup-dataviz
Version: 0.2.0
Summary: 
Author: Ewen Le Bihan
Author-email: ewen.lebihan7@gmail.com
Requires-Python: >=3.6,<4.0
Classifier: Programming Language :: Python :: 3
Classifier: Programming Language :: Python :: 3.6
Classifier: Programming Language :: Python :: 3.7
Classifier: Programming Language :: Python :: 3.8
Requires-Dist: beautifulsoup4 (>=4.9.1,<5.0.0)
Requires-Dist: docopt (>=0.6.2,<0.7.0)
Requires-Dist: helium (>=3.0.4,<4.0.0)
Requires-Dist: lxml (>=4.5.1,<5.0.0)
Requires-Dist: matplotlib (>=3.2.1,<4.0.0)
Requires-Dist: pastel (>=0.2.0,<0.3.0)
Requires-Dist: python-dotenv (>=0.13.0,<0.14.0)
